filesystem_crawler
test
