Metadata-Version: 1.0
Name: filesystem-crawler
Version: 1.1.5
Summary: Search for files or directories that match a set of rules
Home-page: https://github.com/heliosantos/filesystem_crawler
Author: Hélio Santos
Author-email: heliosantos99@gmail.com
License: The MIT License
